README
setup.cfg
setup.py
scikit_credit/__init__.py
scikit_credit.egg-info/PKG-INFO
scikit_credit.egg-info/SOURCES.txt
scikit_credit.egg-info/dependency_links.txt
scikit_credit.egg-info/requires.txt
scikit_credit.egg-info/top_level.txt
scikit_credit/encoder/__init__.py
scikit_credit/encoder/risk_encoder.py
scikit_credit/estimator/__init__.py
scikit_credit/estimator/lr_wrap.py
scikit_credit/estimator/main_wrap.py
scikit_credit/estimator/xgboost_wrap.py
scikit_credit/framework/__init__.py
scikit_credit/framework/bootstrap.py
scikit_credit/metrics/__init__.py
scikit_credit/metrics/corr.py
scikit_credit/metrics/ks.py
scikit_credit/plot/__init__.py
scikit_credit/plot/plot_utils.py
scikit_credit/test/__init__.py
scikit_credit/test/test_encoder.py
scikit_credit/test/test_estimator.py
scikit_credit/test/授信增信项目.py
scikit_credit/utils/__init__.py
scikit_credit/utils/common.py