Metadata-Version: 1.0
Name: scikit-credit
Version: 0.0.22
Summary: scikit-credit for qudian
Home-page: https://git.qufenqi.com/risk-data-scientist/scikit-credit
Author: Yue Ji
Author-email: jiyue@quandian.com
License: MIT
Keywords: scikit credit
Platform: UNKNOWN
